Workbook

Sheet Instructions
A1: Sentinel Firewall local adaptation workbook
A3: Purpose | B3: This workbook accompanies the paper 'The Sentinel Firewall: A Health-System Strategy to Decouple Informal Industrialization from Lead Exposure in LMICs.' The paper asks whether maternal and child health platforms can temporarily reduce lead exposure by replacing contaminated household products with safe substitutes while regulation catches up. This spreadsheet is a simplified local-decision version of that model.
A5: What this tool does | B5: It compares two packages: a Kitchen Package (safe pot, calcium, child utensils) and a Kohl Package (safe maternal and infant kohl). It converts programme delivery into lower maternal and child blood lead levels, child IQ gains, lifetime earnings gains, maternal and neonatal health gains, and secondary adult cardiovascular gains.
A7: Who should use it | B7: This workbook is designed for Ministries of Health, NGOs, environmental health programmes, and local researchers who want to ask a practical question: if local prices, prevalence, attendance, and implementation quality look like our setting, would targeted safe-product substitution likely be worth funding?
A9: How to use it | B9: Go to the Inputs sheet. The grey Default column contains the author's modal assumptions and is locked. Enter local values only in the yellow 'Your local value' column. The green 'Active value' column will automatically use your entry when present and otherwise fall back to the default. The Topline sheet then compares the workbook-default mode-only results with your local mode-only scenario.
A11: What to change first | B11: Start with parameters local decision-makers are most likely to know or influence: GDP per capita, labour share, mortality, product prices, district births and overhead, prevalence in the targeted area, attendance, voucher redemption, stock, and adherence. Scientific parameters such as BLL-to-IQ and IQ-to-earnings are grouped separately and marked 'change cautiously'.
A13: How productivity is defined | B13: Productivity is measured as GDP per capita at purchasing power parity multiplied by labour's share of national income. This values market labour output, including self-employment and informal production that would be missed by observed wages alone. It excludes household production and the intrinsic value of cognition beyond earnings, so the earnings channel remains conservative on that dimension.
A15: Important limitation | B15: This is a deterministic mode-only tool. It does not run the 10,000-draw Monte Carlo uncertainty analysis, does not model parameter correlations, and does not export trial-level data. Use the public Python model for the full probabilistic sensitivity analysis and publication-quality figures.
A17: Public files | B17: Public copies are posted in the Sentinel-Firewall GitHub repository at https://github.com/levine63/Sentinel-Firewall. The main public files are submission_package/public_code_and_data/sentinel_firewall_model.py and submission_package/public_code_and_data/Simulating_sentinel_safe_products.xlsx.

Sheet Inputs
A1: Parameter group | B1: Parameter | C1: Units | D1: Default modal value (locked) | E1: Your local value (edit here) | F1: Active value | G1: Low | H1: High | I1: Why it matters / plain-language description | J1: Citation basis | K1: Change guidance | L1: Internal name
A2: Local macro and demography
A3: Local macro and demography | B3: GDP per capita, PPP | C3: US$ per person per year | D3: 4000 | F3: =IF(LEN(E3)=0,D3,E3) | G3: 2000 | H3: 8000 | I3: PPP GDP per capita | J3: World Bank LMIC context | K3: Usually known locally or from public statistics | L3: gdp_ppp_per_capita
A4: Local macro and demography | B4: Labour share of national income | C4: Share of GDP | D4: 0.55 | F4: =IF(LEN(E4)=0,D4,E4) | G4: 0.5 | H4: 0.58 | I4: Labour share of national income including corrected self-employment income | J4: ILO labour-income-share data with Gollin self-employment correction | K4: Usually known from public macro data or left at default | L4: labor_share_income
A5: Local macro and demography | B5: Real annual productivity growth | C5: Annual rate | D5: 0.02 | F5: =IF(LEN(E5)=0,D5,E5) | G5: 0 | H5: 0.025 | I5: Real annual productivity growth | J5: Long-run LMIC productivity assumption | K5: Change if you have a strong local reason | L5: growth
A6: Local macro and demography | B6: Social discount rate | C6: Annual rate | D6: 0.03 | F6: =IF(LEN(E6)=0,D6,E6) | G6: 0.01 | H6: 0.05 | I6: Social discount rate | J6: Standard economic evaluation range | K6: Policy/evaluation choice | L6: discount
A7: Local macro and demography | B7: Survival from birth to age 18 | C7: Probability | D7: 0.95 | F7: =IF(LEN(E7)=0,D7,E7) | G7: 0.92 | H7: 0.97 | I7: Probability survive to age 18 | J7: World Bank or UN life-table context | K7: Usually known locally or from public statistics | L7: p18
A8: Local macro and demography | B8: Survival from birth to age 65 | C8: Probability | D8: 0.78 | F8: =IF(LEN(E8)=0,D8,E8) | G8: 0.68 | H8: 0.85 | I8: Probability survive to age 65 | J8: World Bank or UN life-table context | K8: Usually known locally or from public statistics | L8: p65
A9: Local macro and demography | B9: Mortality timing shape parameter | C9: Unitless | D9: 2 | F9: =IF(LEN(E9)=0,D9,E9) | G9: 1.5 | H9: 3 | I9: Convexity of survival path | J9: Modeling assumption | K9: Usually leave at default | L9: k
A10: Local macro and demography | B10: Age when earnings begin | C10: Years | D10: 18 | F10: =IF(LEN(E10)=0,D10,E10) | G10: 14 | H10: 20 | I10: Age labor earnings begin | J10: Economic timing assumption | K10: Usually known locally | L10: labor_entry_age
A11: Local macro and demography | B11: Mother age at intervention | C11: Years | D11: 25 | F11: =IF(LEN(E11)=0,D11,E11) | G11: 18 | H11: 35 | I11: Age of mother at intervention | J11: DHS-style fertility timing assumption | K11: Usually known locally | L11: mom_age
A12: Local macro and demography | B12: Grandparent age at intervention | C12: Years | D12: 52 | F12: =IF(LEN(E12)=0,D12,E12) | G12: 42 | H12: 70 | I12: Age of grandparent at intervention | J12: Demographic assumption | K12: Usually leave at default | L12: gp_age
A13: Local macro and demography | B13: Grandparent co-residence | C13: Probability | D13: 0.5 | F13: =IF(LEN(E13)=0,D13,E13) | G13: 0.2 | H13: 0.7 | I13: Probability grandparent coresides | J13: DHS or household survey synthesis | K13: Usually known locally | L13: gp_coresidence_prob
A14: Prices and overhead
A15: Prices and overhead | B15: Lead-safe pot product cost | C15: US$ | D15: 12 | F15: =IF(LEN(E15)=0,D15,E15) | G15: 8 | H15: 15 | I15: Direct product cost of lead-safe pot | J15: Program design costing | K15: Good local input | L15: cost_pot_direct
A16: Prices and overhead | B16: Safe child feeding-utensil product cost | C16: US$ | D16: 1.5 | F16: =IF(LEN(E16)=0,D16,E16) | G16: 1 | H16: 2.5 | I16: Direct product cost of safe utensils | J16: Program design costing | K16: Good local input | L16: cost_utensils_direct
A17: Prices and overhead | B17: Calcium course product cost | C17: US$ | D17: 1.75 | F17: =IF(LEN(E17)=0,D17,E17) | G17: 1.25 | H17: 3 | I17: Direct product cost of calcium course | J17: Program design costing | K17: Good local input | L17: cost_calcium_direct
A18: Prices and overhead | B18: Safe maternal kohl product cost | C18: US$ | D18: 0.75 | F18: =IF(LEN(E18)=0,D18,E18) | G18: 0.4 | H18: 1.25 | I18: Direct product cost of maternal kohl substitute | J18: Program design costing | K18: Good local input | L18: cost_kohl_maternal_direct
A19: Prices and overhead | B19: Safe infant kohl product cost | C19: US$ | D19: 1.5 | F19: =IF(LEN(E19)=0,D19,E19) | G19: 1.2 | H19: 3 | I19: Direct product cost of infant kohl substitute | J19: Program design costing | K19: Good local input | L19: cost_kohl_infant_direct
A20: Prices and overhead | B20: Counseling and explanation cost per contact | C20: US$ | D20: 0.35 | F20: =IF(LEN(E20)=0,D20,E20) | G20: 0.3 | H20: 0.5 | I20: Counseling cost per eligible contact | J20: CHW time assumption | K20: Programme lever | L20: cost_explain
A21: Prices and overhead | B21: Bulk distribution plus retailer margin for pot | C21: US$ | D21: 4 | F21: =IF(LEN(E21)=0,D21,E21) | G21: 3 | H21: 5 | I21: Bulk distribution cost plus retailer margin for pot voucher redemption | J21: Program logistics and merchant margin assumption | K21: Programme lever | L21: cost_bulk_distribution_margin
A22: Prices and overhead | B22: Distribution cost for small item | C22: US$ | D22: 0.5 | F22: =IF(LEN(E22)=0,D22,E22) | G22: 0.25 | H22: 1 | I22: Distribution cost for light items | J22: Program logistics assumption | K22: Programme lever | L22: cost_dist_light
A23: Prices and overhead | B23: Programme overhead markup | C23: Share of direct product plus distribution cost | D23: 0.6 | F23: =IF(LEN(E23)=0,D23,E23) | G23: 0.3 | H23: 1 | I23: Program markup covering wastage supply-chain overhead supervision and health-system administration | J23: Program logistics and administration assumption | K23: Programme lever | L23: logistics_markup
A24: Prices and overhead | B24: National and district fixed programme cost per screening unit | C24: US$ | D24: 50000 | F24: =IF(LEN(E24)=0,D24,E24) | G24: 20000 | H24: 100000 | I24: District fixed cost | J24: Program design assumption | K24: Good local input | L24: district_fixed_cost
A25: Prices and overhead | B25: Births per screening unit | C25: Births | D25: 20000 | F25: =IF(LEN(E25)=0,D25,E25) | G25: 4000 | H25: 50000 | I25: Births per district | J25: Administrative planning assumption | K25: Good local input | L25: district_births
A26: Targeting and prevalence
A27: Targeting and prevalence | B27: Unsafe pot prevalence in targeted households | C27: Share | D27: 0.75 | F27: =IF(LEN(E27)=0,D27,E27) | G27: 0.5 | H27: 0.9 | I27: Unsafe pot prevalence among target households | J27: Hotspot prevalence assumption with improved sentinel targeting | K27: Good local input | L27: prev_pot
A28: Targeting and prevalence | B28: Unsafe maternal kohl prevalence in targeted households | C28: Share | D28: 0.7 | F28: =IF(LEN(E28)=0,D28,E28) | G28: 0.4 | H28: 0.85 | I28: Unsafe maternal kohl prevalence | J28: Synthesized from survey and ethnographic evidence with hotspot targeting | K28: Good local input | L28: prev_kohl_maternal
A29: Targeting and prevalence | B29: Unsafe infant kohl prevalence in targeted households | C29: Share | D29: 0.7 | F29: =IF(LEN(E29)=0,D29,E29) | G29: 0.4 | H29: 0.85 | I29: Unsafe infant kohl prevalence among infants | J29: Synthesized from survey and ethnographic evidence with hotspot targeting | K29: Good local input | L29: prev_kohl_infant
A30: Targeting and prevalence | B30: Unsafe child feeding-utensil prevalence in targeted households | C30: Share | D30: 0.6 | F30: =IF(LEN(E30)=0,D30,E30) | G30: 0.4 | H30: 0.8 | I30: Unsafe utensil prevalence among target households | J30: Context-specific prevalence assumption with improved sentinel targeting | K30: Good local input | L30: prev_utensils
A31: Implementation and programme reach
A32: Implementation and programme reach | B32: Attendance at antenatal care contact | C32: Probability | D32: 0.82 | F32: =IF(LEN(E32)=0,D32,E32) | G32: 0.55 | H32: 0.95 | I32: Attendance at ANC contact | J32: UNICEF ANC coverage benchmarks | K32: Good local input | L32: p_att_anc
A33: Implementation and programme reach | B33: Attendance at 6-month immunization contact | C33: Probability | D33: 0.8 | F33: =IF(LEN(E33)=0,D33,E33) | G33: 0.5 | H33: 0.95 | I33: Attendance at immunization contact | J33: UNICEF or WHO immunization coverage benchmarks | K33: Good local input | L33: p_att_imm
A34: Implementation and programme reach | B34: Institutional delivery contact | C34: Probability | D34: 0.65 | F34: =IF(LEN(E34)=0,D34,E34) | G34: 0.4 | H34: 0.85 | I34: Institutional delivery rate | J34: UNICEF institutional delivery benchmarks | K34: Good local input | L34: p_att_birth
A35: Implementation and programme reach | B35: Infant kohl contact through facility delivery or early immunization | C35: Probability | D35: 0.8 | F35: =IF(LEN(E35)=0,D35,E35) | G35: 0.55 | H35: 0.95 | I35: Infant kohl contact via either facility delivery or early immunization catch-up | J35: Union of correlated infant contacts based on UNICEF delivery and immunization benchmarks | K35: Good local input | L35: p_att_infant_kohl_contact
A36: Implementation and programme reach | B36: Health-system delivery fidelity | C36: Probability | D36: 0.6 | F36: =IF(LEN(E36)=0,D36,E36) | G36: 0.3 | H36: 0.8 | I36: Delivery fidelity | J36: Implementation assumption with service-delivery support | K36: Programme lever | L36: fidelity
A37: Implementation and programme reach | B37: Complete substitution or adherence | C37: Probability | D37: 0.5 | F37: =IF(LEN(E37)=0,D37,E37) | G37: 0.3 | H37: 0.6 | I37: Complete substitution or adherence | J37: Implementation assumption | K37: Programme lever | L37: adherence
A38: Implementation and programme reach | B38: Pot voucher issued at ANC | C38: Probability | D38: 0.7 | F38: =IF(LEN(E38)=0,D38,E38) | G38: 0.4 | H38: 0.9 | I38: Voucher successfully issued at ANC | J38: Program implementation assumption | K38: Programme lever | L38: p_voucher_issued
A39: Implementation and programme reach | B39: Approved merchant has safe pot in stock | C39: Probability | D39: 0.8 | F39: =IF(LEN(E39)=0,D39,E39) | G39: 0.6 | H39: 0.95 | I39: Approved merchant with voucher accepts and has pot in stock | J39: Program implementation assumption | K39: Programme lever | L39: p_merchant_stock
A40: Implementation and programme reach | B40: Pot voucher redeemed | C40: Probability | D40: 0.75 | F40: =IF(LEN(E40)=0,D40,E40) | G40: 0.6 | H40: 0.9 | I40: Voucher redeemed at merchant | J40: Voucher redemption literature and high-value durable good assumption | K40: Programme lever | L40: p_redeem
A41: Implementation and programme reach | B41: Redeemed pot used for pregnant woman or young child | C41: Probability | D41: 0.9 | F41: =IF(LEN(E41)=0,D41,E41) | G41: 0.75 | H41: 0.98 | I41: Redeemed pot used by pregnant woman or toddler | J41: Conditional use after self-targeted redemption | K41: Programme lever | L41: p_use_targeted_after_redemption
A42: Implementation and programme reach | B42: Residual harm from continued unsafe pot use | C42: Share of pot benefit lost | D42: 0.15 | F42: =IF(LEN(E42)=0,D42,E42) | G42: 0.05 | H42: 0.35 | I42: Share of pot benefit lost from continued unsafe pot use for target users | J42: Product stacking penalty | K42: Programme lever | L42: residual_unsafe_use_harm
A43: Product-specific BLL effect sizes
A44: Product-specific BLL effect sizes | B44: Child BLL reduction from full switch to safe pot | C44: ug/dL during active use | D44: 4 | F44: =IF(LEN(E44)=0,D44,E44) | G44: 1 | H44: 10 | I44: Child BLL reduction from pot if fully effective during active use | J44: Widened synthesis assumption from cookware exposure evidence | K44: Change cautiously | L44: bll_pot_child
A45: Product-specific BLL effect sizes | B45: Mother BLL reduction from full switch to safe pot | C45: ug/dL during active use | D45: 2 | F45: =IF(LEN(E45)=0,D45,E45) | G45: 0.5 | H45: 5 | I45: Mother BLL reduction from pot if fully effective during active use | J45: Widened synthesis assumption from cookware exposure evidence | K45: Change cautiously | L45: bll_pot_mother
A46: Product-specific BLL effect sizes | B46: Child BLL reduction from full switch to safe feeding utensils | C46: ug/dL during active use | D46: 2 | F46: =IF(LEN(E46)=0,D46,E46) | G46: 0.5 | H46: 6 | I46: Child BLL reduction from mug or spoon if fully effective during active use | J46: Informed extrapolation with widened uncertainty | K46: Change cautiously | L46: bll_mug_child
A47: Product-specific BLL effect sizes | B47: Mother BLL reduction from calcium | C47: ug/dL during active use | D47: 0.4 | F47: =IF(LEN(E47)=0,D47,E47) | G47: 0.2 | H47: 1.2 | I47: Mother BLL reduction from calcium if fully effective | J47: Ettinger et al. 2009 | K47: Change cautiously | L47: bll_calc_mother
A48: Product-specific BLL effect sizes | B48: Mother BLL reduction from safe maternal kohl | C48: ug/dL during active use | D48: 2 | F48: =IF(LEN(E48)=0,D48,E48) | G48: 0.5 | H48: 5 | I48: Mother BLL reduction from safe maternal kohl if fully effective | J48: Widened synthesized kohl evidence | K48: Change cautiously | L48: bll_maternal_kohl_mother
A49: Product-specific BLL effect sizes | B49: Child BLL reduction from safe infant kohl | C49: ug/dL during active use | D49: 5 | F49: =IF(LEN(E49)=0,D49,E49) | G49: 1.5 | H49: 10 | I49: Child BLL reduction from safe infant kohl if fully effective during active use | J49: Widened synthesized kohl evidence | K49: Change cautiously | L49: bll_infant_kohl_child
A50: Scientific and valuation parameters
A51: Scientific and valuation parameters | B51: IQ gain per 1 ug/dL lower developmental blood lead | C51: IQ points per ug/dL | D51: 0.35 | F51: =IF(LEN(E51)=0,D51,E51) | G51: 0.2 | H51: 0.6 | I51: IQ points gained per 1 ug/dL reduction in developmentally averaged child BLL | J51: Canfield Lanphear Jusko Schnaas plus LMIC contextualization | K51: Change cautiously | L51: iq_per_bll
A52: Scientific and valuation parameters | B52: Earnings gain per IQ point | C52: Share of earnings | D52: 0.005 | F52: =IF(LEN(E52)=0,D52,E52) | G52: 0.003 | H52: 0.01 | I52: Percent earnings gain per IQ point | J52: LMIC-centered range using Ozawa 2022 Grosse et al. 2002 and Hanushek-Woessmann 2008 | K52: Change cautiously | L52: earn_per_iq
A53: Scientific and valuation parameters | B53: Maternal-to-fetal lead reduction transfer | C53: Share | D53: 0.8 | F53: =IF(LEN(E53)=0,D53,E53) | G53: 0.7 | H53: 0.95 | I53: Fraction of maternal lead reduction transmitted to fetal lead reduction | J53: Inferred from maternal-cord lead relationship | K53: Change cautiously | L53: fetal_transfer_coeff
A54: Scientific and valuation parameters | B54: Maternal-to-infant transfer during the milk-dominated first year | C54: Share | D54: 0.2 | F54: =IF(LEN(E54)=0,D54,E54) | G54: 0.1 | H54: 0.35 | I54: Fraction of maternal lead reduction transmitted to the breastfed infant in the milk-dominated first year | J54: Structural bridge from maternal blood lead to early-infancy exposure | K54: Change cautiously | L54: lactational_transfer_coeff
A55: Scientific and valuation parameters | B55: Share of cognitive harm in last four months in utero | C55: Share | D55: 0.3 | F55: =IF(LEN(E55)=0,D55,E55) | G55: 0.2 | H55: 0.4 | I55: Share of developmental cognitive harm attributed to the last four months in utero | J55: Timing-weight assumption informed by prenatal lead literature | K55: Change cautiously | L55: share_prenatal_last4m
A56: Scientific and valuation parameters | B56: Share of cognitive harm in year 1 | C56: Share | D56: 0.3 | F56: =IF(LEN(E56)=0,D56,E56) | G56: 0.2 | H56: 0.4 | I56: Share of developmental cognitive harm attributed to the first year of life | J56: Timing-weight assumption informed by infancy lead literature | K56: Change cautiously | L56: share_year1
A57: Secondary health parameters
A58: Secondary health parameters | B58: Baseline preeclampsia prevalence | C58: Probability | D58: 0.04 | F58: =IF(LEN(E58)=0,D58,E58) | G58: 0.02 | H58: 0.06 | I58: Baseline preeclampsia prevalence | J58: WHO-compatible global burden range | K58: Good local input if available | L58: preeclampsia_base_prev
A59: Secondary health parameters | B59: Preeclampsia odds ratio per 1 ug/dL lead | C59: Odds ratio | D59: 1.018 | F59: =IF(LEN(E59)=0,D59,E59) | G59: 1.016 | H59: 1.02 | I59: Odds ratio per 1 ug/dL lead increase | J59: Poropat et al. 2018 | K59: Change cautiously | L59: preeclampsia_or
A60: Secondary health parameters | B60: Baseline preterm birth prevalence | C60: Probability | D60: 0.12 | F60: =IF(LEN(E60)=0,D60,E60) | G60: 0.08 | H60: 0.15 | I60: Baseline preterm prevalence | J60: WHO preterm birth fact sheet | K60: Good local input if available | L60: preterm_base_prev
A61: Secondary health parameters | B61: Preterm birth odds ratio per 1 ug/dL lead | C61: Odds ratio | D61: 1.025 | F61: =IF(LEN(E61)=0,D61,E61) | G61: 1.02 | H61: 1.03 | I61: Odds ratio per 1 ug/dL lead increase | J61: Prenatal lead birth-outcome synthesis | K61: Change cautiously | L61: preterm_or
A62: Secondary health parameters | B62: Pregnancy timing adjustment for preeclampsia pathway | C62: Share | D62: 0.75 | F62: =IF(LEN(E62)=0,D62,E62) | G62: 0.5 | H62: 1 | I62: Share of full maternal BLL reduction relevant to preeclampsia once intervention starts mid-pregnancy | J62: Timing adjustment for later pregnancy risk window | K62: Change cautiously | L62: preeclampsia_timing_mult
A63: Secondary health parameters | B63: Pregnancy timing adjustment for preterm pathway | C63: Share | D63: 0.7 | F63: =IF(LEN(E63)=0,D63,E63) | G63: 0.4 | H63: 1 | I63: Share of full maternal BLL reduction relevant to preterm birth once intervention starts mid-pregnancy | J63: Timing adjustment for pregnancy-window uncertainty | K63: Change cautiously | L63: preterm_timing_mult
A64: Secondary health parameters | B64: DALYs per preterm birth averted | C64: DALYs | D64: 0.75 | F64: =IF(LEN(E64)=0,D64,E64) | G64: 0.5 | H64: 1 | I64: DALYs per preterm case averted | J64: Reduced-form valuation assumption | K64: Change cautiously | L64: neonatal_daly_mult
A65: Secondary health parameters | B65: Adult cardiovascular DALYs per 1 ug/dL lifetime lead reduction | C65: DALYs | D65: 0.0033 | F65: =IF(LEN(E65)=0,D65,E65) | G65: 0.002 | H65: 0.005 | I65: Lifetime adult DALYs per 1 ug/dL sustained reduction | J65: Lead-CVD burden modeling assumption | K65: Change cautiously | L65: cvd_daly_per_ug_lifetime
A66: Secondary health parameters | B66: Value per DALY relative to annual productivity | C66: Multiplier | D66: 1.6 | F66: =IF(LEN(E66)=0,D66,E66) | G66: 1 | H66: 3 | I66: VSLY multiplier relative to annual productivity | J66: Robinson et al. style valuation range | K66: Policy choice | L66: vsly_mult
A67: Secondary health parameters | B67: DALYs per preeclampsia case | C67: DALYs | D67: 0.003 | F67: =IF(LEN(E67)=0,D67,E67) | G67: 0.001 | H67: 0.005 | I67: DALYs per preeclampsia case | J67: Reduced-form valuation assumption | K67: Change cautiously | L67: preeclampsia_daly_wt
A68: Timing and duration
A69: Timing and duration | B69: Years safe pot protects | C69: Years | D69: 4 | F69: =IF(LEN(E69)=0,D69,E69) | G69: 2 | H69: 5 | I69: Years pot protects | J69: Program duration assumption with widened uncertainty | K69: Good local input if programme design differs | L69: years_pot
A70: Timing and duration | B70: Years safe maternal kohl protects | C70: Years | D70: 1 | F70: =IF(LEN(E70)=0,D70,E70) | G70: 0.5 | H70: 2 | I70: Years maternal kohl protects | J70: Program duration assumption with widened uncertainty | K70: Good local input if programme design differs | L70: years_kohl_maternal
A71: Timing and duration | B71: Years safe infant kohl protects | C71: Years | D71: 1 | F71: =IF(LEN(E71)=0,D71,E71) | G71: 0.5 | H71: 2 | I71: Years infant kohl protects | J71: Program duration assumption with widened uncertainty | K71: Good local input if programme design differs | L71: years_kohl_infant
A72: Timing and duration | B72: Years safe utensils protect | C72: Years | D72: 2 | F72: =IF(LEN(E72)=0,D72,E72) | G72: 1 | H72: 3 | I72: Years utensils protect | J72: Program duration assumption with widened uncertainty | K72: Good local input if programme design differs | L72: years_utensils
A73: Timing and duration | B73: Years calcium affects maternal lead | C73: Years | D73: 0.5 | F73: =IF(LEN(E73)=0,D73,E73) | G73: 0.25 | H73: 1 | I73: Years calcium protects | J73: Program duration assumption with widened uncertainty | K73: Good local input if programme design differs | L73: years_calcium
A74: Timing and duration | B74: Reference age for adult cardiovascular benefits | C74: Years | D74: 65 | F74: =IF(LEN(E74)=0,D74,E74) | G74: 65 | H74: 65 | I74: Reference years for adult cumulative exposure | J74: Modeling assumption | K74: Usually leave at default | L74: adult_reference_years
A75: Timing and duration | B75: Grandparent pot exposure multiplier | C75: Share of child pot effect | D75: 0.5 | F75: =IF(LEN(E75)=0,D75,E75) | G75: 0.5 | H75: 0.5 | I75: Grandparent gets half the pot effect | J75: Modeling assumption | K75: Usually leave at default | L75: gp_pot_effect_multiplier

Sheet Formula_Guide
A1: Concept | B1: Plain-language meaning | C1: Formula used in this workbook | D1: Notes
A2: Present value of lifetime earnings | B2: Expected discounted lifetime earnings from birth. | C2: Productivity x growth/discount adjustment from birth to labour entry x sum of working-year survival and growth/discount terms. | D2: Productivity is GDP PPP per capita x labour share of national income.
A3: Productivity | B3: Annual market-labour output used to value lifetime earnings and VSLY. | C3: GDP per capita, PPP x labour share of national income. | D3: This follows social cost-benefit practice and includes self-employment and informal market production better than observed wages alone.
A4: Pot implementation chain | B4: The safe pot only generates benefit when the household is correctly targeted, reaches ANC, receives a voucher, finds a stocked merchant, redeems the voucher, and uses the pot for the pregnant woman or young child. | C4: Unsafe-pot prevalence x ANC attendance x voucher issued x merchant stocked x voucher redeemed x targeted use x (1 - residual unsafe-use harm). | D4: Costs for the pot are incurred only after attendance, voucher issuance, merchant stock, and redemption; fixed overhead remains regardless.
A5: Clinic-distributed items | B5: Calcium, child utensils, maternal kohl, and infant kohl use shorter delivery chains. | C5: Relevant prevalence where applicable x relevant health-system contact x fidelity x adherence. | D5: Calcium currently helps all reached pregnant women in the targeted area rather than only women with a measured lead source.
A6: Developmental timing | B6: An intervention that lasts only during part of pregnancy or early childhood does not receive the full cognitive benefit of lowering BLL throughout the developmental window. | C6: Prenatal BLL reduction x prenatal share + postnatal BLL reduction x years-protected share. | D6: The default shares are 30% for the last four months in utero, 30% for year 1, and 40% for years 2-5 combined.
A7: IQ gain | B7: Lower developmentally weighted child blood lead increases expected IQ. | C7: Developmentally weighted child BLL reduction x IQ gain per 1 ug/dL lower BLL. | D7: The full Python model also reports a nonlinear log-BLL robustness check.
A8: Lifetime earnings gain | B8: IQ gains raise expected lifetime earnings. | C8: Present value of lifetime earnings x earnings gain per IQ point x IQ gain. | D8: This is the main cognition-channel social benefit.
A9: Benefit-cost ratio | B9: Social benefits divided by programme costs. | C9: Benefits / costs. | D9: The Topline sheet compares the workbook-default mode-only run with your local mode-only run for cognition-only, maternal/neonatal, and total BCRs.

Sheet PV_Helper
A1: Working year | B1: Survival S_t (default) | C1: Survival S_t (local) | D1: Growth-discount factor (default) | E1: Growth-discount factor (local) | F1: Included in work life (default) | G1: Included in work life (local) | H1: PV term (default) | I1: PV term (local)
A2: 1 | B2: =Inputs!$D$7-(Inputs!$D$7-Inputs!$D$8)*POWER((A2-1)/47,Inputs!$D$9) | C2: =Inputs!$F$7-(Inputs!$F$7-Inputs!$F$8)*POWER((A2-1)/47,Inputs!$F$9) | D2: =POWER(((1+Inputs!$D$5)/(1+Inputs!$D$6)),A2-1) | E2: =POWER(((1+Inputs!$F$5)/(1+Inputs!$F$6)),A2-1) | F2: =--(A2<=(65-Inputs!$D$10+1)) | G2: =--(A2<=(65-Inputs!$F$10+1)) | H2: =B2*D2*F2 | I2: =C2*E2*G2
A3: 2 | B3: =Inputs!$D$7-(Inputs!$D$7-Inputs!$D$8)*POWER((A3-1)/47,Inputs!$D$9) | C3: =Inputs!$F$7-(Inputs!$F$7-Inputs!$F$8)*POWER((A3-1)/47,Inputs!$F$9) | D3: =POWER(((1+Inputs!$D$5)/(1+Inputs!$D$6)),A3-1) | E3: =POWER(((1+Inputs!$F$5)/(1+Inputs!$F$6)),A3-1) | F3: =--(A3<=(65-Inputs!$D$10+1)) | G3: =--(A3<=(65-Inputs!$F$10+1)) | H3: =B3*D3*F3 | I3: =C3*E3*G3
A4: 3 | B4: =Inputs!$D$7-(Inputs!$D$7-Inputs!$D$8)*POWER((A4-1)/47,Inputs!$D$9) | C4: =Inputs!$F$7-(Inputs!$F$7-Inputs!$F$8)*POWER((A4-1)/47,Inputs!$F$9) | D4: =POWER(((1+Inputs!$D$5)/(1+Inputs!$D$6)),A4-1) | E4: =POWER(((1+Inputs!$F$5)/(1+Inputs!$F$6)),A4-1) | F4: =--(A4<=(65-Inputs!$D$10+1)) | G4: =--(A4<=(65-Inputs!$F$10+1)) | H4: =B4*D4*F4 | I4: =C4*E4*G4
A5: 4 | B5: =Inputs!$D$7-(Inputs!$D$7-Inputs!$D$8)*POWER((A5-1)/47,Inputs!$D$9) | C5: =Inputs!$F$7-(Inputs!$F$7-Inputs!$F$8)*POWER((A5-1)/47,Inputs!$F$9) | D5: =POWER(((1+Inputs!$D$5)/(1+Inputs!$D$6)),A5-1) | E5: =POWER(((1+Inputs!$F$5)/(1+Inputs!$F$6)),A5-1) | F5: =--(A5<=(65-Inputs!$D$10+1)) | G5: =--(A5<=(65-Inputs!$F$10+1)) | H5: =B5*D5*F5 | I5: =C5*E5*G5
A6: 5 | B6: =Inputs!$D$7-(Inputs!$D$7-Inputs!$D$8)*POWER((A6-1)/47,Inputs!$D$9) | C6: =Inputs!$F$7-(Inputs!$F$7-Inputs!$F$8)*POWER((A6-1)/47,Inputs!$F$9) | D6: =POWER(((1+Inputs!$D$5)/(1+Inputs!$D$6)),A6-1) | E6: =POWER(((1+Inputs!$F$5)/(1+Inputs!$F$6)),A6-1) | F6: =--(A6<=(65-Inputs!$D$10+1)) | G6: =--(A6<=(65-Inputs!$F$10+1)) | H6: =B6*D6*F6 | I6: =C6*E6*G6
A7: 6 | B7: =Inputs!$D$7-(Inputs!$D$7-Inputs!$D$8)*POWER((A7-1)/47,Inputs!$D$9) | C7: =Inputs!$F$7-(Inputs!$F$7-Inputs!$F$8)*POWER((A7-1)/47,Inputs!$F$9) | D7: =POWER(((1+Inputs!$D$5)/(1+Inputs!$D$6)),A7-1) | E7: =POWER(((1+Inputs!$F$5)/(1+Inputs!$F$6)),A7-1) | F7: =--(A7<=(65-Inputs!$D$10+1)) | G7: =--(A7<=(65-Inputs!$F$10+1)) | H7: =B7*D7*F7 | I7: =C7*E7*G7
A8: 7 | B8: =Inputs!$D$7-(Inputs!$D$7-Inputs!$D$8)*POWER((A8-1)/47,Inputs!$D$9) | C8: =Inputs!$F$7-(Inputs!$F$7-Inputs!$F$8)*POWER((A8-1)/47,Inputs!$F$9) | D8: =POWER(((1+Inputs!$D$5)/(1+Inputs!$D$6)),A8-1) | E8: =POWER(((1+Inputs!$F$5)/(1+Inputs!$F$6)),A8-1) | F8: =--(A8<=(65-Inputs!$D$10+1)) | G8: =--(A8<=(65-Inputs!$F$10+1)) | H8: =B8*D8*F8 | I8: =C8*E8*G8
A9: 8 | B9: =Inputs!$D$7-(Inputs!$D$7-Inputs!$D$8)*POWER((A9-1)/47,Inputs!$D$9) | C9: =Inputs!$F$7-(Inputs!$F$7-Inputs!$F$8)*POWER((A9-1)/47,Inputs!$F$9) | D9: =POWER(((1+Inputs!$D$5)/(1+Inputs!$D$6)),A9-1) | E9: =POWER(((1+Inputs!$F$5)/(1+Inputs!$F$6)),A9-1) | F9: =--(A9<=(65-Inputs!$D$10+1)) | G9: =--(A9<=(65-Inputs!$F$10+1)) | H9: =B9*D9*F9 | I9: =C9*E9*G9
A10: 9 | B10: =Inputs!$D$7-(Inputs!$D$7-Inputs!$D$8)*POWER((A10-1)/47,Inputs!$D$9) | C10: =Inputs!$F$7-(Inputs!$F$7-Inputs!$F$8)*POWER((A10-1)/47,Inputs!$F$9) | D10: =POWER(((1+Inputs!$D$5)/(1+Inputs!$D$6)),A10-1) | E10: =POWER(((1+Inputs!$F$5)/(1+Inputs!$F$6)),A10-1) | F10: =--(A10<=(65-Inputs!$D$10+1)) | G10: =--(A10<=(65-Inputs!$F$10+1)) | H10: =B10*D10*F10 | I10: =C10*E10*G10
A11: 10 | B11: =Inputs!$D$7-(Inputs!$D$7-Inputs!$D$8)*POWER((A11-1)/47,Inputs!$D$9) | C11: =Inputs!$F$7-(Inputs!$F$7-Inputs!$F$8)*POWER((A11-1)/47,Inputs!$F$9) | D11: =POWER(((1+Inputs!$D$5)/(1+Inputs!$D$6)),A11-1) | E11: =POWER(((1+Inputs!$F$5)/(1+Inputs!$F$6)),A11-1) | F11: =--(A11<=(65-Inputs!$D$10+1)) | G11: =--(A11<=(65-Inputs!$F$10+1)) | H11: =B11*D11*F11 | I11: =C11*E11*G11
A12: 11 | B12: =Inputs!$D$7-(Inputs!$D$7-Inputs!$D$8)*POWER((A12-1)/47,Inputs!$D$9) | C12: =Inputs!$F$7-(Inputs!$F$7-Inputs!$F$8)*POWER((A12-1)/47,Inputs!$F$9) | D12: =POWER(((1+Inputs!$D$5)/(1+Inputs!$D$6)),A12-1) | E12: =POWER(((1+Inputs!$F$5)/(1+Inputs!$F$6)),A12-1) | F12: =--(A12<=(65-Inputs!$D$10+1)) | G12: =--(A12<=(65-Inputs!$F$10+1)) | H12: =B12*D12*F12 | I12: =C12*E12*G12
A13: 12 | B13: =Inputs!$D$7-(Inputs!$D$7-Inputs!$D$8)*POWER((A13-1)/47,Inputs!$D$9) | C13: =Inputs!$F$7-(Inputs!$F$7-Inputs!$F$8)*POWER((A13-1)/47,Inputs!$F$9) | D13: =POWER(((1+Inputs!$D$5)/(1+Inputs!$D$6)),A13-1) | E13: =POWER(((1+Inputs!$F$5)/(1+Inputs!$F$6)),A13-1) | F13: =--(A13<=(65-Inputs!$D$10+1)) | G13: =--(A13<=(65-Inputs!$F$10+1)) | H13: =B13*D13*F13 | I13: =C13*E13*G13
... A53: 52 | B53: =Inputs!$D$7-(Inputs!$D$7-Inputs!$D$8)*POWER((A53-1)/47,Inputs!$D$9) | C53: =Inputs!$F$7-(Inputs!$F$7-Inputs!$F$8)*POWER((A53-1)/47,Inputs!$F$9) | D53: =POWER(((1+Inputs!$D$5)/(1+Inputs!$D$6)),A53-1) | E53: =POWER(((1+Inputs!$F$5)/(1+Inputs!$F$6)),A53-1) | F53: =--(A53<=(65-Inputs!$D$10+1)) | G53: =--(A53<=(65-Inputs!$F$10+1)) | H53: =B53*D53*F53 | I53: =C53*E53*G53

Sheet Results
A1: Detailed deterministic calculations
A2: Default paper values | B2: Default | C2: Your local run | D2: Notes
A3: productivity | B3: =Inputs!$D$3*Inputs!$D$4 | C3: =Inputs!$F$3*Inputs!$F$4 | D3: GDP PPP per capita x labour share of national income
A4: x_growth_discount | B4: =((1+Inputs!$D$5)/(1+Inputs!$D$6)) | C4: =((1+Inputs!$F$5)/(1+Inputs!$F$6)) | D4: (1+growth)/(1+discount)
A5: pv_earnings | B5: =B3*POWER(B4,Inputs!$D$10)*SUM(PV_Helper!H2:H53) | C5: =C3*POWER(C4,Inputs!$F$10)*SUM(PV_Helper!I2:I53)
A6: fixed_cost_per_birth | B6: =Inputs!$D$24/Inputs!$D$25 | C6: =Inputs!$F$24/Inputs!$F$25
A7: vsly | B7: =Inputs!$D$66*B3 | C7: =Inputs!$F$66*C3
A8: share_years2to5 | B8: =1-Inputs!$D$55-Inputs!$D$56 | C8: =1-Inputs!$F$55-Inputs!$F$56
A9: post_weight_pot | B9: =Inputs!$D$56*MIN(Inputs!$D$69,0.5)+B8*(MIN(MAX(Inputs!$D$69-0.5,0),4)/4) | C9: =Inputs!$F$56*MIN(Inputs!$F$69,0.5)+C8*(MIN(MAX(Inputs!$F$69-0.5,0),4)/4)
A10: post_weight_utensils | B10: =Inputs!$D$56*MIN(Inputs!$D$72,0.5)+B8*(MIN(MAX(Inputs!$D$72-0.5,0),4)/4) | C10: =Inputs!$F$56*MIN(Inputs!$F$72,0.5)+C8*(MIN(MAX(Inputs!$F$72-0.5,0),4)/4)
A11: post_weight_kohl_infant | B11: =Inputs!$D$56*MIN(Inputs!$D$71,1)+B8*(MIN(MAX(Inputs!$D$71-1,0),4)/4) | C11: =Inputs!$F$56*MIN(Inputs!$F$71,1)+C8*(MIN(MAX(Inputs!$F$71-1,0),4)/4)
A13: Kitchen package | D13: Default and local deterministic runs
A14: k_p_success_pot | B14: =Inputs!$D$27*Inputs!$D$32*Inputs!$D$38*Inputs!$D$39*Inputs!$D$40*Inputs!$D$41 | C14: =Inputs!$F$27*Inputs!$F$32*Inputs!$F$38*Inputs!$F$39*Inputs!$F$40*Inputs!$F$41
A15: k_p_success_pot_after_residual | B15: =B14*(1-Inputs!$D$42) | C15: =C14*(1-Inputs!$F$42)
A16: k_p_success_calcium | B16: =Inputs!$D$32*Inputs!$D$36*Inputs!$D$37 | C16: =Inputs!$F$32*Inputs!$F$36*Inputs!$F$37
A17: k_p_success_utensils | B17: =Inputs!$D$30*Inputs!$D$33*Inputs!$D$36*Inputs!$D$37 | C17: =Inputs!$F$30*Inputs!$F$33*Inputs!$F$36*Inputs!$F$37
A18: k_eff_bll_pot_child | B18: =Inputs!$D$44*B15 | C18: =Inputs!$F$44*C15
A19: k_eff_bll_pot_mother | B19: =Inputs!$D$45*B15 | C19: =Inputs!$F$45*C15
A20: k_eff_bll_calcium_mother | B20: =Inputs!$D$47*B16 | C20: =Inputs!$F$47*C16
A21: k_eff_bll_utensils_child | B21: =Inputs!$D$46*B17 | C21: =Inputs!$F$46*C17
A22: k_eff_bll_prenatal_child | B22: =Inputs!$D$53*(B19+B20) | C22: =Inputs!$F$53*(C19+C20)
A23: k_eff_bll_lactational_child | B23: =Inputs!$D$54*B19 | C23: =Inputs!$F$54*C19
A24: k_eff_bll_child_total | B24: =B18+B21+B22+B23 | C24: =C18+C21+C22+C23
A25: k_eff_bll_child_cog_equiv | B25: =B22*Inputs!$D$55+B23*Inputs!$D$56*MIN(Inputs!$D$69,1)+B18*B9+B21*B10 | C25: =C22*Inputs!$F$55+C23*Inputs!$F$56*MIN(Inputs!$F$69,1)+C18*C9+C21*C10
A26: k_delta_iq | B26: =B25*Inputs!$D$51 | C26: =C25*Inputs!$F$51
A27: k_benefit_earnings | B27: =B5*Inputs!$D$52*B26 | C27: =C5*Inputs!$F$52*C26
A28: k_preeclampsia_delta | B28: =Inputs!$D$58-((Inputs!$D$58/(1-Inputs!$D$58))/POWER(Inputs!$D$59,(B19+B20)*Inputs!$D$62))/(1+((Inputs!$D$58/(1-Inputs!$D$58))/POWER(Inputs!$D$59,(B19+B20)*Inputs!$D$62))) | C28: =Inputs!$F$58-((Inputs!$F$58/(1-Inputs!$F$58))/POWER(Inputs!$F$59,(C19+C20)*Inputs!$F$62))/(1+((Inputs!$F$58/(1-Inputs!$F$58))/POWER(Inputs!$F$59,(C19+C20)*Inputs!$F$62)))
A29: k_preterm_delta | B29: =Inputs!$D$60-((Inputs!$D$60/(1-Inputs!$D$60))/POWER(Inputs!$D$61,(B19+B20)*Inputs!$D$63))/(1+((Inputs!$D$60/(1-Inputs!$D$60))/POWER(Inputs!$D$61,(B19+B20)*Inputs!$D$63))) | C29: =Inputs!$F$60-((Inputs!$F$60/(1-Inputs!$F$60))/POWER(Inputs!$F$61,(C19+C20)*Inputs!$F$63))/(1+((Inputs!$F$60/(1-Inputs!$F$60))/POWER(Inputs!$F$61,(C19+C20)*Inputs!$F$63)))
A30: k_benefit_maternal_neonatal | B30: =B28*Inputs!$D$67*B7+B29*Inputs!$D$64*B7 | C30: =C28*Inputs!$F$67*C7+C29*Inputs!$F$64*C7
A31: k_benefit_cvd | B31: =((B19*Inputs!$D$69+B20*Inputs!$D$73)*Inputs!$D$65*B7*POWER(1+Inputs!$D$6,-MAX(0,Inputs!$D$74-Inputs!$D$11)))+(B18*Inputs!$D$65*Inputs!$D$69*B7*Inputs!$D$75*POWER(1+Inputs!$D$6,-MAX(0,Inputs!$D$74-Inputs!$D$12))*Inputs!$D$13) | C31: =((C19*Inputs!$F$69+C20*Inputs!$F$73)*Inputs!$F$65*C7*POWER(1+Inputs!$F$6,-MAX(0,Inputs!$F$74-Inputs!$F$11)))+(C18*Inputs!$F$65*Inputs!$F$69*C7*Inputs!$F$75*POWER(1+Inputs!$F$6,-MAX(0,Inputs!$F$74-Inputs!$F$12))*Inputs!$F$13)
A32: k_cost | B32: =B6+Inputs!$D$20*Inputs!$D$32+(Inputs!$D$15+Inputs!$D$21)*(1+Inputs!$D$23)*Inputs!$D$32*Inputs!$D$38*Inputs!$D$39*Inputs!$D$40+Inputs!$D$20*Inputs!$D$32+Inputs!$D$22*(1+Inputs!$D$23)*Inputs!$D$32*Inputs!$D$36+Inputs!$D$17*(1+Inputs!$D$23)*Inputs!$D$32*Inputs!$D$36+Inputs!$D$20*Inputs!$D$33+Inputs!$D$22*(1+Inputs!$D$23)*Inputs!$D$33*Inputs!$D$36+Inputs!$D$16*(1+Inputs!$D$23)*Inputs!$D$33*Inputs!$D$36 | C32: =C6+Inputs!$F$20*Inputs!$F$32+(Inputs!$F$15+Inputs!$F$21)*(1+Inputs!$F$23)*Inputs!$F$32*Inputs!$F$38*Inputs!$F$39*Inputs!$F$40+Inputs!$F$20*Inputs!$F$32+Inputs!$F$22*(1+Inputs!$F$23)*Inputs!$F$32*Inputs!$F$36+Inputs!$F$17*(1+Inputs!$F$23)*Inputs!$F$32*Inputs!$F$36+Inputs!$F$20*Inputs!$F$33+Inputs!$F$22*(1+Inputs!$F$23)*Inputs!$F$33*Inputs!$F$36+Inputs!$F$16*(1+Inputs!$F$23)*Inputs!$F$33*Inputs!$F$36
A33: k_bcr_cog | B33: =B27/B32 | C33: =C27/C32
A34: k_bcr_plus_mn | B34: =(B27+B30)/B32 | C34: =(C27+C30)/C32
A35: k_bcr_total | B35: =(B27+B30+B31)/B32 | C35: =(C27+C30+C31)/C32
A37: Kohl package | D37: Default and local deterministic runs
A38: ko_p_success_maternal | B38: =Inputs!$D$28*Inputs!$D$32*Inputs!$D$36*Inputs!$D$37 | C38: =Inputs!$F$28*Inputs!$F$32*Inputs!$F$36*Inputs!$F$37
A39: ko_p_success_infant | B39: =Inputs!$D$29*Inputs!$D$35*Inputs!$D$36*Inputs!$D$37 | C39: =Inputs!$F$29*Inputs!$F$35*Inputs!$F$36*Inputs!$F$37
A40: ko_eff_bll_mother | B40: =Inputs!$D$48*B38 | C40: =Inputs!$F$48*C38
A41: ko_eff_bll_infant | B41: =Inputs!$D$49*B39 | C41: =Inputs!$F$49*C39
A42: ko_eff_bll_prenatal_child | B42: =Inputs!$D$53*B40 | C42: =Inputs!$F$53*C40
A43: ko_eff_bll_lactational_child | B43: =Inputs!$D$54*B40 | C43: =Inputs!$F$54*C40
A44: ko_eff_bll_child_total | B44: =B42+B43+B41 | C44: =C42+C43+C41
A45: ko_eff_bll_child_cog_equiv | B45: =B42*Inputs!$D$55+B43*Inputs!$D$56*MIN(Inputs!$D$70,1)+B41*B11 | C45: =C42*Inputs!$F$55+C43*Inputs!$F$56*MIN(Inputs!$F$70,1)+C41*C11
A46: ko_delta_iq | B46: =B45*Inputs!$D$51 | C46: =C45*Inputs!$F$51
A47: ko_benefit_earnings | B47: =B5*Inputs!$D$52*B46 | C47: =C5*Inputs!$F$52*C46
A48: ko_preeclampsia_delta | B48: =Inputs!$D$58-((Inputs!$D$58/(1-Inputs!$D$58))/POWER(Inputs!$D$59,B40*Inputs!$D$62))/(1+((Inputs!$D$58/(1-Inputs!$D$58))/POWER(Inputs!$D$59,B40*Inputs!$D$62))) | C48: =Inputs!$F$58-((Inputs!$F$58/(1-Inputs!$F$58))/POWER(Inputs!$F$59,C40*Inputs!$F$62))/(1+((Inputs!$F$58/(1-Inputs!$F$58))/POWER(Inputs!$F$59,C40*Inputs!$F$62)))
A49: ko_preterm_delta | B49: =Inputs!$D$60-((Inputs!$D$60/(1-Inputs!$D$60))/POWER(Inputs!$D$61,B40*Inputs!$D$63))/(1+((Inputs!$D$60/(1-Inputs!$D$60))/POWER(Inputs!$D$61,B40*Inputs!$D$63))) | C49: =Inputs!$F$60-((Inputs!$F$60/(1-Inputs!$F$60))/POWER(Inputs!$F$61,C40*Inputs!$F$63))/(1+((Inputs!$F$60/(1-Inputs!$F$60))/POWER(Inputs!$F$61,C40*Inputs!$F$63)))
A50: ko_benefit_maternal_neonatal | B50: =B48*Inputs!$D$67*B7+B49*Inputs!$D$64*B7 | C50: =C48*Inputs!$F$67*C7+C49*Inputs!$F$64*C7
A51: ko_benefit_cvd | B51: =B40*Inputs!$D$65*Inputs!$D$70*B7*POWER(1+Inputs!$D$6,-MAX(0,Inputs!$D$74-Inputs!$D$11)) | C51: =C40*Inputs!$F$65*Inputs!$F$70*C7*POWER(1+Inputs!$F$6,-MAX(0,Inputs!$F$74-Inputs!$F$11))
A52: ko_cost | B52: =B6+Inputs!$D$20*Inputs!$D$32+Inputs!$D$22*(1+Inputs!$D$23)*Inputs!$D$32*Inputs!$D$36+Inputs!$D$18*Inputs!$D$70*(1+Inputs!$D$23)*Inputs!$D$32*Inputs!$D$36+Inputs!$D$20*Inputs!$D$35+Inputs!$D$22*(1+Inputs!$D$23)*Inputs!$D$35*Inputs!$D$36+Inputs!$D$19*(1+Inputs!$D$23)*Inputs!$D$35*Inputs!$D$36 | C52: =C6+Inputs!$F$20*Inputs!$F$32+Inputs!$F$22*(1+Inputs!$F$23)*Inputs!$F$32*Inputs!$F$36+Inputs!$F$18*Inputs!$F$70*(1+Inputs!$F$23)*Inputs!$F$32*Inputs!$F$36+Inputs!$F$20*Inputs!$F$35+Inputs!$F$22*(1+Inputs!$F$23)*Inputs!$F$35*Inputs!$F$36+Inputs!$F$19*(1+Inputs!$F$23)*Inputs!$F$35*Inputs!$F$36
A53: ko_bcr_cog | B53: =B47/B52 | C53: =C47/C52
A54: ko_bcr_plus_mn | B54: =(B47+B50)/B52 | C54: =(C47+C50)/C52
A55: ko_bcr_total | B55: =(B47+B50+B51)/B52 | C55: =(C47+C50+C51)/C52

Sheet Topline
A1: Output | B1: Units | C1: Paper default: Kitchen | D1: Your local run: Kitchen | E1: Paper default: Kohl | F1: Your local run: Kohl
A2: Cost per mother-child pair | B2: US$ | C2: =Results!$B$32 | D2: =Results!$C$32 | E2: =Results!$B$52 | F2: =Results!$C$52
A3: Present value of lifetime earnings gain per child | B3: US$ | C3: =Results!$B$27 | D3: =Results!$C$27 | E3: =Results!$B$47 | F3: =Results!$C$47
A4: Benefit-cost ratio, cognition channel only | B4: Ratio | C4: =Results!$B$33 | D4: =Results!$C$33 | E4: =Results!$B$53 | F4: =Results!$C$53
A5: Benefit-cost ratio, cognition, maternal health, and neonatal health channels | B5: Ratio | C5: =Results!$B$34 | D5: =Results!$C$34 | E5: =Results!$B$54 | F5: =Results!$C$54
A6: Benefit-cost ratio, cognition, maternal health, neonatal health, and cardiovascular illness channels | B6: Ratio | C6: =Results!$B$35 | D6: =Results!$C$35 | E6: =Results!$B$55 | F6: =Results!$C$55
A7: Child BLL reduction during intervention period | B7: ug/dL | C7: =Results!$B$24 | D7: =Results!$C$24 | E7: =Results!$B$44 | F7: =Results!$C$44
A8: Developmentally weighted child blood lead reduction used for cognition calculation | B8: ug/dL | C8: =Results!$B$25 | D8: =Results!$C$25 | E8: =Results!$B$45 | F8: =Results!$C$45
A9: Child IQ gain | B9: IQ points | C9: =Results!$B$26 | D9: =Results!$C$26 | E9: =Results!$B$46 | F9: =Results!$C$46
